{
  "totalReports": 184,
  "totalFeatures": 2849,
  "totalScenarios": 10125,
  "totalSteps": 122939,
  "totalPassed": 121328,
  "totalFailed": 332,
  "totalSkipped": 1279,
  "totalDuration": 184962.63059869976,
  "totalSize": 99722723,
  "averageDuration": "1005.23",
  "passRate": "98.69",
  "failRate": "0.27",
  "skipRate": "1.04",
  "oldestReport": {
    "id": "gct-20250725-060624",
    "name": "GeoCall Automation Test Results Report",
    "date": "2025-07-25T00:36:24.000Z",
    "size": 201167,
    "features": 15,
    "scenarios": 52,
    "steps": 659,
    "passed": 659,
    "failed": 0,
    "skipped": 0,
    "duration": 926.0620481,
    "tags": [
      "AddResponse",
      "AddResponseFlowValidation",
      "AuthDashBoard",
      "AuthTicket",
      "CreateTicket",
      "EndToEndSuite",
      "Excavators",
      "ExistingUserData",
      "HomeOwnerTicket",
      "MyCompanyTickets",
      "OpenTicketInResponses",
      "PrintTicket",
      "QuickTestSuite",
      "RegressionSuite",
      "RememberMe",
      "ResetPassword",
      "Responses",
      "RunNow",
      "SignIn",
      "SignUp",
      "TicketDrafts",
      "TicketSearch",
      "UnAuthDashBoard",
      "ViewTicketDetails",
      "WorkAreaWithPolygon"
    ],
    "environment": null,
    "tool": null,
    "version": null,
    "hash": "9070cfb6ae22d2083d44f48e2335d40c",
    "suggestedFilename": "gct-20250725-060624.json",
    "status": "active",
    "isDeleted": false
  },
  "newestReport": {
    "id": "gct-20260325-043645",
    "name": "GeoCall Automation Test Results Report",
    "date": "2026-03-24T23:06:45.000Z",
    "size": 115942,
    "features": 16,
    "scenarios": 59,
    "steps": 688,
    "passed": 688,
    "failed": 0,
    "skipped": 0,
    "duration": 1095.4149106,
    "tags": [
      "AddResponse",
      "AddResponseFlowValidation",
      "AuthDashBoard",
      "AuthTicket",
      "CreateTicket",
      "EndToEndSuite",
      "Excavators",
      "ExistingUserData",
      "HomeOwnerTicket",
      "MyCompanyTickets",
      "OpenTicketInResponses",
      "PrintTicket",
      "QuickTestSuite",
      "RegressionSuite",
      "RememberMe",
      "ResetPassword",
      "Responses",
      "RunNow",
      "SignIn",
      "SignUp",
      "TicketDrafts",
      "TicketSearch",
      "UnAuthDashBoard",
      "ViewTicketDetails",
      "WorkAreaWithPolygon"
    ],
    "environment": null,
    "tool": null,
    "version": null,
    "hash": "9f94000d675b91b03e8fb744058cb731",
    "suggestedFilename": "gct-20260325-043645.json",
    "status": "active",
    "isDeleted": false
  },
  "allTags": [
    "AddResponse",
    "AddResponseFlowValidation",
    "AuthDashBoard",
    "AuthTicket",
    "CreateTicket",
    "EndToEndSuite",
    "Excavators",
    "ExistingUserData",
    "HomeOwnerTicket",
    "MyCompanyTickets",
    "OpenTicketInResponses",
    "PrintTicket",
    "QuickTestSuite",
    "RegressionSuite",
    "RememberMe",
    "ResetPassword",
    "Responses",
    "RunNow",
    "SignIn",
    "SignUp",
    "TicketDrafts",
    "TicketSearch",
    "UnAuthDashBoard",
    "ViewTicketDetails",
    "WorkAreaWithPolygon"
  ],
  "environments": [],
  "tools": []
}